visionarypm/__init__.py
visionarypm/words.txt
visionarypm-6.3.4.dist-info/DESCRIPTION.rst
visionarypm-6.3.4.dist-info/METADATA
visionarypm-6.3.4.dist-info/RECORD
visionarypm-6.3.4.dist-info/WHEEL
visionarypm-6.3.4.dist-info/entry_points.txt
visionarypm-6.3.4.dist-info/metadata.json
visionarypm-6.3.4.dist-info/top_level.txt
